bar_chart_race/__init__.py
bar_chart_race/_colormaps.py
bar_chart_race/_make_chart.py
tests/__init__.py
tests/test_bar_charts.py
tests/test_prepare.py
bar_chart_race-0.1.0.dist-info/LICENSE
bar_chart_race-0.1.0.dist-info/METADATA
bar_chart_race-0.1.0.dist-info/WHEEL
bar_chart_race-0.1.0.dist-info/top_level.txt
bar_chart_race-0.1.0.dist-info/RECORD
