Metadata-Version: 2.1
Name: bar_chart_race
Version: 0.1.0
Summary: Create animated bar chart races using matplotlib
Home-page: https://github.com/dexplo/bar_chart_race
Author: Ted Petrou
Author-email: petrou.theodore@gmail.com
License: MIT
Keywords: visualization animation bar chart race matplotlib pandas
Platform: UNKNOWN
Classifier: Programming Language :: Python :: 3
Classifier: License :: OSI Approved :: MIT License
Classifier: Operating System :: OS Independent
Requires-Python: >=3.6
